pprinting/__init__.py
pprinting/get_dir_size.py
pprinting/printTab.py
pprinting/str_tools.py
pprinting/write_log.py
pprinting-1.5.dist-info/LICENSE
pprinting-1.5.dist-info/METADATA
pprinting-1.5.dist-info/WHEEL
pprinting-1.5.dist-info/top_level.txt
pprinting-1.5.dist-info/RECORD
